ollama_tools/__init__.py
ollama_tools/core.py
ollama_tools/server.py
ollama_tools-1.0.2.dist-info/LICENSE
ollama_tools-1.0.2.dist-info/METADATA
ollama_tools-1.0.2.dist-info/WHEEL
ollama_tools-1.0.2.dist-info/entry_points.txt
ollama_tools-1.0.2.dist-info/top_level.txt
ollama_tools-1.0.2.dist-info/RECORD
