Metadata-Version: 2.2
Name: ollama-tools
Version: 1.0.2
Summary: A workaround for models on Ollama that does not support tool calling
Home-page: https://github.com/NewJerseyStyle
Author: Yuan XU
Author-email: dev.source@outlook.com
License: MIT License
License-File: LICENSE
Requires-Dist: pydantic
Requires-Dist: ollama
Provides-Extra: full
Requires-Dist: fastapi; extra == "full"
Requires-Dist: uvicorn; extra == "full"
Dynamic: author
Dynamic: author-email
Dynamic: description
Dynamic: description-content-type
Dynamic: home-page
Dynamic: license
Dynamic: provides-extra
Dynamic: requires-dist
Dynamic: summary
